amiqus/__init__.py
amiqus/admin.py
amiqus/api.py
amiqus/apps.py
amiqus/decorators.py
amiqus/helpers.py
amiqus/management/__init__.py
amiqus/migrations/0001_initial.py
amiqus/migrations/0002_record_perform_url_alter_record_status.py
amiqus/migrations/0003_alter_client_status.py
amiqus/migrations/0004_update_check_types.py
amiqus/migrations/0005_form_step_review.py
amiqus/migrations/0006_step_amiqus_id.py
amiqus/migrations/__init__.py
amiqus/models/__init__.py
amiqus/models/base.py
amiqus/models/check.py
amiqus/models/client.py
amiqus/models/event.py
amiqus/models/form.py
amiqus/models/record.py
amiqus/models/review.py
amiqus/models/step.py
amiqus/settings.py
amiqus/signals.py
amiqus/types.py
amiqus/urls.py
amiqus/views.py
django_amiqus-0.5.dist-info/LICENSE
django_amiqus-0.5.dist-info/METADATA
django_amiqus-0.5.dist-info/WHEEL
django_amiqus-0.5.dist-info/RECORD
