Metadata-Version: 2.3
Name: django-amiqus
Version: 0.5
Summary: Django app for integration with Amiqus.
License: MIT
Author: YunoJuno
Author-email: code@yunojuno.com
Maintainer: YunoJuno
Maintainer-email: code@yunojuno.com
Requires-Python: >=3.12,<4.0
Classifier: Development Status :: 4 - Beta
Classifier: Environment :: Web Environment
Classifier: Framework :: Django
Classifier: Framework :: Django :: 5.2
Classifier: Framework :: Django :: 6.0
Classifier: License :: OSI Approved :: MIT License
Classifier: Operating System :: OS Independent
Classifier: Programming Language :: Python :: 3
Classifier: Programming Language :: Python :: 3.12
Classifier: Programming Language :: Python :: 3.13
Classifier: Programming Language :: Python :: 3 :: Only
Requires-Dist: django (>=5.2,<7.0)
Requires-Dist: python-dateutil
Requires-Dist: requests
Requires-Dist: simplejson
Project-URL: Documentation, https://github.com/yunojuno/django-amiqus
Project-URL: Homepage, https://github.com/yunojuno/django-amiqus
Project-URL: Repository, https://github.com/yunojuno/django-amiqus
